pyflies_ls/__init__.py
pyflies_ls/__main__.py
pyflies_ls/pyflies_ls.py
pyflies_ls/util.py
pyflies_ls/features/__init__.py
pyflies_ls/features/code_actions.py
pyflies_ls/features/completion.py
pyflies_ls/features/definitions.py
pyflies_ls/features/references.py
pyflies_ls/features/validate.py
pyflies_ls-0.0.3.dist-info/LICENSE
pyflies_ls-0.0.3.dist-info/METADATA
pyflies_ls-0.0.3.dist-info/WHEEL
pyflies_ls-0.0.3.dist-info/top_level.txt
pyflies_ls-0.0.3.dist-info/RECORD
