Metadata-Version: 2.1
Name: pyflies-ls
Version: 0.0.3
Summary: a language server for pyFlies language
Home-page: https://github.com/DejanS24/pyflies-LS
Author: Dejan Sorgic
Author-email: dejans1224@gmail.com
Keywords: pyFlies DSL python domain specific languages language server protocol pygls
Classifier: Intended Audience :: Developers
Classifier: Intended Audience :: Information Technology
Classifier: Topic :: Software Development :: Libraries :: Python Modules
Classifier: Operating System :: OS Independent
Classifier: Programming Language :: Python :: 3 :: Only
Classifier: Programming Language :: Python :: 3.5
Classifier: Programming Language :: Python :: 3.6
Classifier: Programming Language :: Python :: 3.7
Classifier: Programming Language :: Python :: 3.8
License-File: LICENSE
Requires-Dist: pygls ==1.0.2
Requires-Dist: textx
Requires-Dist: pyflies
